README.md
setup.py
pydomosed/__init__.py
pydomosed/__version__.py
pydomosed/base.py
pydomosed/hooks.py
pydomosed.egg-info/PKG-INFO
pydomosed.egg-info/SOURCES.txt
pydomosed.egg-info/dependency_links.txt
pydomosed.egg-info/not-zip-safe
pydomosed.egg-info/requires.txt
pydomosed.egg-info/top_level.txt