Metadata-Version: 2.1
Name: pydomosed
Version: 0.1.0
Summary: pydomosed — Python Domosed API Wrapper
Home-page: https://github.com/evtn/pydomosed
Author: evtn
Author-email: g@evtn.ru
License: Do What The F*ck You Want To Public License
Download-URL: https://github.com/evtn/pydomosed/archive/v0.1.0.tar.gz
Keywords: domosed api vk
Platform: UNKNOWN
Classifier: Development Status :: 4 - Beta
Classifier: Intended Audience :: Developers
Classifier: Programming Language :: Python :: 3
Classifier: Programming Language :: Python :: 3.6
Classifier: Programming Language :: Python :: 3.7
Classifier: Programming Language :: Python :: 3.8
Classifier: Programming Language :: Python :: 3.9
Requires-Python: >=3.6.*
